setup.py
izzati/__init__.py
izzati/frontend.py
izzati/main.py
izzati.egg-info/PKG-INFO
izzati.egg-info/SOURCES.txt
izzati.egg-info/dependency_links.txt
izzati.egg-info/not-zip-safe
izzati.egg-info/requires.txt
izzati.egg-info/top_level.txt