Metadata-Version: 1.1
Name: izzati
Version: 1.1.0
Summary: A simple, multi-language frontend to backend communication library
Home-page: http://github.com/kusti8/izzati
Author: Gustav Hansen
Author-email: kusti8@gmail.com
License: GPL3
Keywords: izzati backend frontend communication simple
Platform: UNKNOWN
Classifier: Development Status :: 5 - Production/Stable
Classifier: License :: OSI Approved :: GNU General Public License v3 or later (GPLv3+)
Classifier: Programming Language :: Python :: 3 :: Only
